aws_cost_optimization_2/__init__.py
aws_cost_optimization_2/utils.py
aws_cost_optimization_2-0.1.5.dist-info/LICENCE
aws_cost_optimization_2-0.1.5.dist-info/METADATA
aws_cost_optimization_2-0.1.5.dist-info/WHEEL
aws_cost_optimization_2-0.1.5.dist-info/top_level.txt
aws_cost_optimization_2-0.1.5.dist-info/RECORD
